cumulus/__init__.py
cumulus/cloudformation_builder.py
cumulus/cumulus.py
cumulus/types.py
cumulus/chain/__init__.py
cumulus/chain/chain.py
cumulus/chain/chaincontext.py
cumulus/chain/params.py
cumulus/chain/step.py
cumulus/components/__init__.py
cumulus/components/userdata/__init__.py
cumulus/components/userdata/linux.py
cumulus/components/userdata/windows.py
cumulus/policies/__init__.py
cumulus/policies/cloudformation.py
cumulus/policies/codebuild.py
cumulus/steps/__init__.py
cumulus/steps/resource.py
cumulus/steps/dev_tools/__init__.py
cumulus/steps/dev_tools/approval_action.py
cumulus/steps/dev_tools/cloud_formation_action.py
cumulus/steps/dev_tools/code_build_action.py
cumulus/steps/dev_tools/lambda_action.py
cumulus/steps/dev_tools/pipeline.py
cumulus/steps/dev_tools/pipeline_source_action.py
cumulus/steps/dev_tools/pipeline_source_action_code_commit.py
cumulus/steps/dev_tools/pipeline_stage.py
cumulus/steps/dev_tools/vpc_config.py
cumulus/steps/ec2/__init__.py
cumulus/steps/ec2/alb.py
cumulus/steps/ec2/alb_port.py
cumulus/steps/ec2/block_device_data.py
cumulus/steps/ec2/dns.py
cumulus/steps/ec2/ingress_rule.py
cumulus/steps/ec2/instance_profile_policy.py
cumulus/steps/ec2/launch_config.py
cumulus/steps/ec2/listener_rule.py
cumulus/steps/ec2/scaling_group.py
cumulus/steps/ec2/target_group.py
cumulus/steps/storage/__init__.py
cumulus/steps/storage/s3bucket.py
cumulus/types/__init__.py
cumulus/types/cloudformation/__init__.py
cumulus/types/cloudformation/action_mode.py
cumulus/types/codebuild/__init__.py
cumulus/types/codebuild/buildaction.py
cumulus/util/__init__.py
cumulus/util/policy_mutator.py
cumulus/util/template_query.py
tests/stacker_test/__init__.py
tests/stacker_test/delete_bucket_versions.py
tests/stacker_test/run-integration.sh
tests/stacker_test/stacker.yaml
tests/stacker_test/blueprints/__init__.py
tests/stacker_test/blueprints/alb.py
tests/stacker_test/blueprints/pipeline_simple.py
tests/stacker_test/blueprints/s3_bucket.py
cfn_cumulus-0.1.18.dist-info/AUTHORS.rst
cfn_cumulus-0.1.18.dist-info/LICENSE
cfn_cumulus-0.1.18.dist-info/METADATA
cfn_cumulus-0.1.18.dist-info/WHEEL
cfn_cumulus-0.1.18.dist-info/top_level.txt
cfn_cumulus-0.1.18.dist-info/RECORD
