Metadata-Version: 2.1
Name: cfn-cumulus
Version: 0.1.18
Summary: Simplified Cloudformation architectural patterns, with an opinion
Home-page: https://github.com/brettswift/cumulus
Author: Brett Swift
Author-email: brettswift@gmail.com
License: MIT license
Keywords: cumulus
Platform: UNKNOWN
Classifier: Development Status :: 2 - Pre-Alpha
Classifier: Intended Audience :: Developers
Classifier: License :: OSI Approved :: MIT License
Classifier: Natural Language :: English
Classifier: Programming Language :: Python :: 2
Classifier: Programming Language :: Python :: 2.7
Classifier: Programming Language :: Python :: 3
Classifier: Programming Language :: Python :: 3.6
Classifier: Programming Language :: Python :: 3.7
Requires-Dist: troposphere
Requires-Dist: awacs
Requires-Dist: termcolor
Requires-Dist: enum34
Provides-Extra: test
Requires-Dist: pytest ; extra == 'test'
Requires-Dist: pytest-runner ; extra == 'test'
Requires-Dist: stacker ; extra == 'test'
Requires-Dist: flake8 ; extra == 'test'
Requires-Dist: pytest-watch ; extra == 'test'
Requires-Dist: coveralls ; extra == 'test'
Requires-Dist: awscli ; extra == 'test'
Requires-Dist: mock ; extra == 'test'
